{
  "NAS100_USD": {
    "base": {
      "label": "unfiltered",
      "total_sfps": 4945,
      "traded": 4938,
      "timed_out": 7,
      "wins": 2443,
      "losses": 2495,
      "win_rate": 0.4947,
      "avg_pnl_r": -0.0105,
      "total_r": -52.0,
      "profit_factor": 0.979,
      "sharpe_r": -0.167,
      "avg_bars_held": 6.8
    },
    "ewmac": {
      "label": "ewmac\u22655.0",
      "total_sfps": 2725,
      "traded": 2722,
      "timed_out": 3,
      "wins": 1366,
      "losses": 1356,
      "win_rate": 0.5018,
      "avg_pnl_r": 0.0037,
      "total_r": 10.0,
      "profit_factor": 1.007,
      "sharpe_r": 0.058,
      "avg_bars_held": 7.0
    },
    "sma200": {
      "label": "sma200",
      "total_sfps": 3089,
      "traded": 3086,
      "timed_out": 3,
      "wins": 1539,
      "losses": 1547,
      "win_rate": 0.4987,
      "avg_pnl_r": -0.0026,
      "total_r": -8.0,
      "profit_factor": 0.995,
      "sharpe_r": -0.041,
      "avg_bars_held": 6.9
    },
    "both": {
      "label": "ewmac+sma200",
      "total_sfps": 2695,
      "traded": 2692,
      "timed_out": 3,
      "wins": 1351,
      "losses": 1341,
      "win_rate": 0.5019,
      "avg_pnl_r": 0.0037,
      "total_r": 10.0,
      "profit_factor": 1.007,
      "sharpe_r": 0.059,
      "avg_bars_held": 7.1
    }
  },
  "SPX500_USD": {
    "base": {
      "label": "unfiltered",
      "total_sfps": 4761,
      "traded": 4751,
      "timed_out": 10,
      "wins": 2333,
      "losses": 2418,
      "win_rate": 0.4911,
      "avg_pnl_r": -0.0179,
      "total_r": -85.0,
      "profit_factor": 0.965,
      "sharpe_r": -0.284,
      "avg_bars_held": 6.8
    },
    "ewmac": {
      "label": "ewmac\u22655.0",
      "total_sfps": 2772,
      "traded": 2767,
      "timed_out": 5,
      "wins": 1378,
      "losses": 1389,
      "win_rate": 0.498,
      "avg_pnl_r": -0.004,
      "total_r": -11.0,
      "profit_factor": 0.992,
      "sharpe_r": -0.063,
      "avg_bars_held": 7.1
    },
    "sma200": {
      "label": "sma200",
      "total_sfps": 2972,
      "traded": 2967,
      "timed_out": 5,
      "wins": 1485,
      "losses": 1482,
      "win_rate": 0.5005,
      "avg_pnl_r": 0.001,
      "total_r": 3.0,
      "profit_factor": 1.002,
      "sharpe_r": 0.016,
      "avg_bars_held": 7.1
    },
    "both": {
      "label": "ewmac+sma200",
      "total_sfps": 2703,
      "traded": 2698,
      "timed_out": 5,
      "wins": 1344,
      "losses": 1354,
      "win_rate": 0.4981,
      "avg_pnl_r": -0.0037,
      "total_r": -10.0,
      "profit_factor": 0.993,
      "sharpe_r": -0.059,
      "avg_bars_held": 7.1
    }
  },
  "UK100_GBP": {
    "base": {
      "label": "unfiltered",
      "total_sfps": 3685,
      "traded": 3675,
      "timed_out": 10,
      "wins": 1842,
      "losses": 1833,
      "win_rate": 0.5012,
      "avg_pnl_r": 0.0024,
      "total_r": 9.0,
      "profit_factor": 1.005,
      "sharpe_r": 0.039,
      "avg_bars_held": 6.0
    },
    "ewmac": {
      "label": "ewmac\u22655.0",
      "total_sfps": 1750,
      "traded": 1743,
      "timed_out": 7,
      "wins": 891,
      "losses": 852,
      "win_rate": 0.5112,
      "avg_pnl_r": 0.0224,
      "total_r": 39.0,
      "profit_factor": 1.046,
      "sharpe_r": 0.355,
      "avg_bars_held": 5.9
    },
    "sma200": {
      "label": "sma200",
      "total_sfps": 2126,
      "traded": 2117,
      "timed_out": 9,
      "wins": 1073,
      "losses": 1044,
      "win_rate": 0.5068,
      "avg_pnl_r": 0.0137,
      "total_r": 29.0,
      "profit_factor": 1.028,
      "sharpe_r": 0.217,
      "avg_bars_held": 5.9
    },
    "both": {
      "label": "ewmac+sma200",
      "total_sfps": 1726,
      "traded": 1719,
      "timed_out": 7,
      "wins": 881,
      "losses": 838,
      "win_rate": 0.5125,
      "avg_pnl_r": 0.025,
      "total_r": 43.0,
      "profit_factor": 1.051,
      "sharpe_r": 0.397,
      "avg_bars_held": 5.9
    }
  },
  "EUR_USD": {
    "base": {
      "label": "unfiltered",
      "total_sfps": 4806,
      "traded": 4790,
      "timed_out": 16,
      "wins": 2396,
      "losses": 2394,
      "win_rate": 0.5002,
      "avg_pnl_r": 0.0004,
      "total_r": 2.0,
      "profit_factor": 1.001,
      "sharpe_r": 0.007,
      "avg_bars_held": 6.1
    },
    "ewmac": {
      "label": "ewmac\u22655.0",
      "total_sfps": 1771,
      "traded": 1766,
      "timed_out": 5,
      "wins": 924,
      "losses": 842,
      "win_rate": 0.5232,
      "avg_pnl_r": 0.0464,
      "total_r": 82.0,
      "profit_factor": 1.097,
      "sharpe_r": 0.738,
      "avg_bars_held": 6.1
    },
    "sma200": {
      "label": "sma200",
      "total_sfps": 2126,
      "traded": 2120,
      "timed_out": 6,
      "wins": 1096,
      "losses": 1024,
      "win_rate": 0.517,
      "avg_pnl_r": 0.034,
      "total_r": 72.0,
      "profit_factor": 1.07,
      "sharpe_r": 0.539,
      "avg_bars_held": 6.0
    },
    "both": {
      "label": "ewmac+sma200",
      "total_sfps": 1719,
      "traded": 1714,
      "timed_out": 5,
      "wins": 903,
      "losses": 811,
      "win_rate": 0.5268,
      "avg_pnl_r": 0.0537,
      "total_r": 92.0,
      "profit_factor": 1.113,
      "sharpe_r": 0.853,
      "avg_bars_held": 6.1
    }
  },
  "GBP_USD": {
    "base": {
      "label": "unfiltered",
      "total_sfps": 4972,
      "traded": 4958,
      "timed_out": 14,
      "wins": 2418,
      "losses": 2540,
      "win_rate": 0.4877,
      "avg_pnl_r": -0.0246,
      "total_r": -122.0,
      "profit_factor": 0.952,
      "sharpe_r": -0.391,
      "avg_bars_held": 6.2
    },
    "ewmac": {
      "label": "ewmac\u22655.0",
      "total_sfps": 1770,
      "traded": 1766,
      "timed_out": 4,
      "wins": 894,
      "losses": 872,
      "win_rate": 0.5062,
      "avg_pnl_r": 0.0125,
      "total_r": 22.0,
      "profit_factor": 1.025,
      "sharpe_r": 0.198,
      "avg_bars_held": 6.2
    },
    "sma200": {
      "label": "sma200",
      "total_sfps": 2375,
      "traded": 2370,
      "timed_out": 5,
      "wins": 1180,
      "losses": 1190,
      "win_rate": 0.4979,
      "avg_pnl_r": -0.0042,
      "total_r": -10.0,
      "profit_factor": 0.992,
      "sharpe_r": -0.067,
      "avg_bars_held": 6.2
    },
    "both": {
      "label": "ewmac+sma200",
      "total_sfps": 1703,
      "traded": 1699,
      "timed_out": 4,
      "wins": 862,
      "losses": 837,
      "win_rate": 0.5074,
      "avg_pnl_r": 0.0147,
      "total_r": 25.0,
      "profit_factor": 1.03,
      "sharpe_r": 0.234,
      "avg_bars_held": 6.3
    }
  },
  "USD_JPY": {
    "base": {
      "label": "unfiltered",
      "total_sfps": 3584,
      "traded": 3550,
      "timed_out": 34,
      "wins": 1752,
      "losses": 1798,
      "win_rate": 0.4935,
      "avg_pnl_r": -0.013,
      "total_r": -46.0,
      "profit_factor": 0.974,
      "sharpe_r": -0.206,
      "avg_bars_held": 6.0
    },
    "ewmac": {
      "label": "ewmac\u22655.0",
      "total_sfps": 1653,
      "traded": 1633,
      "timed_out": 20,
      "wins": 802,
      "losses": 831,
      "win_rate": 0.4911,
      "avg_pnl_r": -0.0178,
      "total_r": -29.0,
      "profit_factor": 0.965,
      "sharpe_r": -0.282,
      "avg_bars_held": 5.9
    },
    "sma200": {
      "label": "sma200",
      "total_sfps": 1754,
      "traded": 1734,
      "timed_out": 20,
      "wins": 869,
      "losses": 865,
      "win_rate": 0.5012,
      "avg_pnl_r": 0.0023,
      "total_r": 4.0,
      "profit_factor": 1.005,
      "sharpe_r": 0.037,
      "avg_bars_held": 6.0
    },
    "both": {
      "label": "ewmac+sma200",
      "total_sfps": 1581,
      "traded": 1564,
      "timed_out": 17,
      "wins": 781,
      "losses": 783,
      "win_rate": 0.4994,
      "avg_pnl_r": -0.0013,
      "total_r": -2.0,
      "profit_factor": 0.997,
      "sharpe_r": -0.02,
      "avg_bars_held": 6.0
    }
  },
  "XAU_USD": {
    "base": {
      "label": "unfiltered",
      "total_sfps": 4221,
      "traded": 4204,
      "timed_out": 17,
      "wins": 2048,
      "losses": 2156,
      "win_rate": 0.4872,
      "avg_pnl_r": -0.0257,
      "total_r": -108.0,
      "profit_factor": 0.95,
      "sharpe_r": -0.408,
      "avg_bars_held": 6.3
    },
    "ewmac": {
      "label": "ewmac\u22655.0",
      "total_sfps": 2091,
      "traded": 2081,
      "timed_out": 10,
      "wins": 1044,
      "losses": 1037,
      "win_rate": 0.5017,
      "avg_pnl_r": 0.0034,
      "total_r": 7.0,
      "profit_factor": 1.007,
      "sharpe_r": 0.053,
      "avg_bars_held": 6.1
    },
    "sma200": {
      "label": "sma200",
      "total_sfps": 2601,
      "traded": 2589,
      "timed_out": 12,
      "wins": 1303,
      "losses": 1286,
      "win_rate": 0.5033,
      "avg_pnl_r": 0.0066,
      "total_r": 17.0,
      "profit_factor": 1.013,
      "sharpe_r": 0.104,
      "avg_bars_held": 6.4
    },
    "both": {
      "label": "ewmac+sma200",
      "total_sfps": 2028,
      "traded": 2018,
      "timed_out": 10,
      "wins": 1020,
      "losses": 998,
      "win_rate": 0.5055,
      "avg_pnl_r": 0.0109,
      "total_r": 22.0,
      "profit_factor": 1.022,
      "sharpe_r": 0.173,
      "avg_bars_held": 6.2
    }
  },
  "BTC_USD": {
    "base": {
      "label": "unfiltered",
      "total_sfps": 4285,
      "traded": 4259,
      "timed_out": 26,
      "wins": 2052,
      "losses": 2207,
      "win_rate": 0.4818,
      "avg_pnl_r": -0.0364,
      "total_r": -155.0,
      "profit_factor": 0.93,
      "sharpe_r": -0.578,
      "avg_bars_held": 6.4
    },
    "ewmac": {
      "label": "ewmac\u22655.0",
      "total_sfps": 2053,
      "traded": 2043,
      "timed_out": 10,
      "wins": 983,
      "losses": 1060,
      "win_rate": 0.4812,
      "avg_pnl_r": -0.0377,
      "total_r": -77.0,
      "profit_factor": 0.927,
      "sharpe_r": -0.599,
      "avg_bars_held": 6.5
    },
    "sma200": {
      "label": "sma200",
      "total_sfps": 2572,
      "traded": 2559,
      "timed_out": 13,
      "wins": 1211,
      "losses": 1348,
      "win_rate": 0.4732,
      "avg_pnl_r": -0.0535,
      "total_r": -137.0,
      "profit_factor": 0.898,
      "sharpe_r": -0.851,
      "avg_bars_held": 6.5
    },
    "both": {
      "label": "ewmac+sma200",
      "total_sfps": 2035,
      "traded": 2025,
      "timed_out": 10,
      "wins": 974,
      "losses": 1051,
      "win_rate": 0.481,
      "avg_pnl_r": -0.038,
      "total_r": -77.0,
      "profit_factor": 0.927,
      "sharpe_r": -0.604,
      "avg_bars_held": 6.5
    }
  }
}